{
	"format_version": "1.8.0",
	"animations": {
		"walk": {
			"loop": true,
			"animation_length": 2,
			"bones": {
				"right_arm": {
					"rotation": {
						"0.0": {
							"vector": [0, 0, 0]
						},
						"1.0": {
							"vector": [37.5, 0, 0],
							"easing": "easeInOutSine"
						},
						"2.0": {
							"vector": [0, 0, 0],
							"easing": "easeInOutSine"
						}
					}
				},
				"left_arm": {
					"rotation": {
						"0.0": {
							"vector": [37.5, 0, 0]
						},
						"1.0": {
							"vector": [0, 0, 0],
							"easing": "easeInOutSine"
						},
						"2.0": {
							"vector": [37.5, 0, 0],
							"easing": "easeInOutSine"
						}
					},
					"position": {
						"vector": [0, 0, 1.3]
					}
				},
				"rightLeg": {
					"rotation": {
						"0.0": {
							"vector": [-35, 0, 0]
						},
						"1.0": {
							"vector": [35, 0, 0],
							"easing": "easeInOutSine"
						},
						"2.0": {
							"vector": [-35, 0, 0],
							"easing": "easeInOutSine"
						}
					}
				},
				"leftLeg": {
					"rotation": {
						"0.0": {
							"vector": [35, 0, 0]
						},
						"1.0": {
							"vector": [-35, 0, 0],
							"easing": "easeInOutSine"
						},
						"2.0": {
							"vector": [35, 0, 0],
							"easing": "easeInOutSine"
						}
					}
				},
				"mechaRight": {
					"rotation": {
						"0.0": {
							"vector": [35, 0, 0]
						},
						"1.0": {
							"vector": [-35, 0, 0],
							"easing": "easeInOutSine"
						},
						"2.0": {
							"vector": [35, 0, 0],
							"easing": "easeInOutSine"
						}
					}
				},
				"mechaLeft": {
					"rotation": {
						"0.0": {
							"vector": [-35, 0, 0]
						},
						"1.0": {
							"vector": [35, 0, 0],
							"easing": "easeInOutSine"
						},
						"2.0": {
							"vector": [-35, 0, 0],
							"easing": "easeInOutSine"
						}
					}
				},
				"mekkron": {
					"rotation": {
						"0.0": {
							"vector": [0, 0, -1]
						},
						"1.0": {
							"vector": [0, 0, 1],
							"easing": "easeInOutSine"
						},
						"2.0": {
							"vector": [0, 0, -1],
							"easing": "easeInOutSine"
						}
					},
					"position": {
						"0.0": {
							"vector": [0, 0, 0]
						},
						"0.4583": {
							"vector": [0, 1, 0],
							"easing": "easeInOutSine"
						},
						"1.0": {
							"vector": [0, 0, 0],
							"easing": "easeInOutSine"
						},
						"1.5": {
							"vector": [0, 1, 0],
							"easing": "easeInOutSine"
						},
						"2.0": {
							"vector": [0, 0, 0],
							"easing": "easeInOutSine"
						}
					}
				}
			}
		},
		"aggresive": {
			"loop": true,
			"animation_length": 1,
			"bones": {
				"rightLeg": {
					"rotation": {
						"0.0": {
							"vector": [-35, 0, 0]
						},
						"0.5": {
							"vector": [35, 0, 0],
							"easing": "easeInOutSine"
						},
						"1.0": {
							"vector": [-35, 0, 0],
							"easing": "easeInOutSine"
						}
					}
				},
				"leftLeg": {
					"rotation": {
						"0.0": {
							"vector": [35, 0, 0]
						},
						"0.5": {
							"vector": [-35, 0, 0],
							"easing": "easeInOutSine"
						},
						"1.0": {
							"vector": [35, 0, 0],
							"easing": "easeInOutSine"
						}
					}
				},
				"mechaRight": {
					"rotation": {
						"0.0": {
							"vector": [-175, 0, 0]
						},
						"0.5": {
							"vector": [-130, 0, 0],
							"easing": "easeInOutSine"
						},
						"1.0": {
							"vector": [-175, 0, 0],
							"easing": "easeInOutSine"
						}
					}
				},
				"mechaLeft": {
					"rotation": {
						"0.0": {
							"vector": [-135, 0, 0]
						},
						"0.5": {
							"vector": [-182.5, 0, 0],
							"easing": "easeInOutSine"
						},
						"1.0": {
							"vector": [-135, 0, 0],
							"easing": "easeInOutSine"
						}
					}
				},
				"mekkron": {
					"rotation": {
						"0.0": {
							"vector": [0, 0, -1]
						},
						"0.5": {
							"vector": [0, 0, 1],
							"easing": "easeInOutSine"
						},
						"1.0": {
							"vector": [0, 0, -1],
							"easing": "easeInOutSine"
						}
					},
					"position": {
						"0.0": {
							"vector": [0, 0, 0]
						},
						"0.25": {
							"vector": [0, 1, 0],
							"easing": "easeInOutSine"
						},
						"0.5": {
							"vector": [0, 0, 0],
							"easing": "easeInOutSine"
						},
						"0.75": {
							"vector": [0, 1, 0],
							"easing": "easeInOutSine"
						},
						"1.0": {
							"vector": [0, 0, 0],
							"easing": "easeInOutSine"
						}
					}
				},
				"right_arm": {
					"rotation": {
						"0.0": {
							"vector": [0, 0, 0]
						},
						"0.5": {
							"vector": [37.5, 0, 0],
							"easing": "easeInOutSine"
						},
						"1.0": {
							"vector": [0, 0, 0],
							"easing": "easeInOutSine"
						}
					}
				},
				"left_arm": {
					"rotation": {
						"0.0": {
							"vector": [37.5, 0, 0]
						},
						"0.5": {
							"vector": [0, 0, 0],
							"easing": "easeInOutSine"
						},
						"1.0": {
							"vector": [37.5, 0, 0],
							"easing": "easeInOutSine"
						}
					},
					"position": {
						"vector": [0, 0, 1.3]
					}
				}
			}
		},
		"attack": {
			"animation_length": 1.25,
			"bones": {
				"mechaBody": {
					"rotation": {
						"0.0": {
							"vector": [0, 0, 0]
						},
						"0.375": {
							"vector": [42.5, 0, 0]
						},
						"1.25": {
							"vector": [0, 0, 0]
						}
					},
					"position": {
						"0.0": {
							"vector": [0, 0, 0]
						},
						"0.375": {
							"vector": [0, 2, 19]
						},
						"1.25": {
							"vector": [0, 0, 0]
						}
					}
				},
				"mechaRight": {
					"rotation": {
						"0.0": {
							"vector": [-175, 0, 0]
						},
						"0.2083": {
							"vector": [-73.1403, -20.40336, 15.74785]
						},
						"1.25": {
							"vector": [-175, 0, 0]
						}
					}
				},
				"mechaLeft": {
					"rotation": {
						"0.0": {
							"vector": [-175, 0, 0]
						},
						"0.2083": {
							"vector": [-73.15159, 20.38619, -19.48491]
						},
						"1.25": {
							"vector": [-175, 0, 0]
						}
					}
				}
			}
		},
		"attack2": {
			"animation_length": 1.25,
			"bones": {
				"mechaBody": {
					"rotation": {
						"0.0": {
							"vector": [0, 0, 0]
						},
						"0.375": {
							"vector": [42.5, 0, 0]
						},
						"1.25": {
							"vector": [0, 0, 0]
						}
					},
					"position": {
						"0.0": {
							"vector": [0, 0, 0]
						},
						"0.375": {
							"vector": [0, 2, 19]
						},
						"1.25": {
							"vector": [0, 0, 0]
						}
					}
				},
				"mechaRight": {
					"rotation": {
						"0.0": {
							"vector": [-175, 0, 0]
						},
						"0.2083": {
							"vector": [-73.1403, -20.40336, 15.74785]
						},
						"1.25": {
							"vector": [-175, 0, 0]
						}
					}
				}
			}
		},
		"idle": {
			"loop": true
		}
	},
	"geckolib_format_version": 2
}